loss_balancer_tf/__init__.py
loss_balancer_tf/loss_balancer_tf.py
loss_balancer_tf-0.0.4.dist-info/LICENSE
loss_balancer_tf-0.0.4.dist-info/METADATA
loss_balancer_tf-0.0.4.dist-info/WHEEL
loss_balancer_tf-0.0.4.dist-info/top_level.txt
loss_balancer_tf-0.0.4.dist-info/RECORD
