Metadata-Version: 2.1
Name: loss-balancer-tf
Version: 0.0.4
Summary: Implementation of Encodec loss balancer in tensorflow
Author: anime-song
License: MIT license
License-File: LICENSE
Requires-Dist: tensorflow
